chem_balancer/__init__.py
chem_balancer/balancer.py
chemical_eq_balancer-0.4.dist-info/LICENSE
chemical_eq_balancer-0.4.dist-info/METADATA
chemical_eq_balancer-0.4.dist-info/WHEEL
chemical_eq_balancer-0.4.dist-info/top_level.txt
chemical_eq_balancer-0.4.dist-info/RECORD
