Metadata-Version: 2.1
Name: chemical_eq_balancer
Version: 0.4
Summary: a package to balance simple chemical equations
Home-page: https://github.com/amirhossein2831/Chim_Eq_Balancer
Author: AmirHossein
Author-email: amirmemool12@gmail.com
License: MIT
License-File: LICENSE
Requires-Dist: numpy
